{
  "DashboardDefinitionRoles": [],
  "Id": "98d1297b-dc86-497f-9f76-6eaf397edcb3",
  "Name": "Recursos",
  "Active": true,
  "Location": 0,
  "DocumentId": "00000000-0000-0000-0000-000000000000",
  "DocumentName": "",
  "DocumentTypeName": null,
  "DocumentsConfiguration": "{}",
  "Templates": [],
  "DashboardDefinitionComponents": [
    {
      "Id": "990d911a-55f7-400e-b6c3-033b344cd7f7",
      "Name": "Selector de datas",
      "Active": true,
      "UseQuery": false,
      "Query": null,
      "Size": 2,
      "Order": 0,
      "Parameters": "[{\"WidgetSubTitle\":\"\",\"WidgetType\":\"dateselector\",\"WidgetFilterField\":\"\",\"WidgetColor\":\"#ffffff\",\"WidgetFrameStyle\":{},\"WidgetXPosition\":39,\"WidgetYPosition\":0,\"WidgetRows\":2,\"WidgetColumns\":9,\"WidgetHeader\":{\"showContextInfo\":false,\"WidgetPeriodChooser\":{\"type\":\"year\",\"visible\":false},\"WidgetMetrics\":{\"visible\":false,\"Metrics\":[]},\"showSubTitle\":false,\"showTitle\":false},\"WidgetDataSources\":{\"main\":{\"type\":\"querytext\",\"value\":\"\",\"mapping\":\"\"}},\"Filters\":{},\"QueryConfiguration\":{}}]",
      "DashboardComponentType": {
        "Id": "be9c4895-90b8-4755-9054-caa7770b6a09",
        "Name": "Generic Dashboard",
        "ComponentTypeNumber": 42
      },
      "AnalyticsApiUrl": null,
      "Configuration": "{\r\n    \"shift\": {\r\n        \"unit\": \"month\",\r\n        \"value\": \"1\"\r\n    },\r\n    \"width\": \"250px\",\r\n    \"calendarOptions\": {\r\n        \"maxZoomLevel\": \"year\",\r\n        \"minZoomLevel\": \"century\"\r\n    },\r\n    \"onContentReady\": \"function(e) { \r\n        SW.saveComponent(e, \u0027Range\u0027);\r\n        var selectBox = SW.getComponent(\u0027timePreset\u0027);\r\n        var today = new Date(); \r\n               \r\n        switch(selectBox) {                                                                        \r\n            case \u0027Hour\u0027:              \r\n            var unit = \u0027day\u0027; \r\n            e.component.option(\u0027displayFormat\u0027).type = \u0027dd MMMM\u0027;      \r\n            e.component.option(\u0027shift\u0027).unit = unit;  \r\n            e.component.option(\u0027shift\u0027).value = 1;  \r\n\r\n                break;                                                                 \r\n            \r\n            case \u0027Day\u0027:                 \r\n            var unit = \u0027week\u0027;          \r\n                break;                     \r\n            \r\n            case \u0027Week\u0027:                \r\n            var unit = \u0027month\u0027;\r\n\r\n                break;                                       \r\n            \r\n            case \u0027Month\u0027:                 \r\n                var unit = \u0027year\u0027;   \r\n                var firstDayOfMonth = new Date(today.getFullYear(), today.getMonth(),\r\n        1);\r\n                var lastDayOfMonth = new Date(today.getFullYear(), today.getMonth(),\r\n        30);\r\n                \r\n                e.component.option(\u0027value\u0027, firstDayOfMonth);\r\n                SkillsWorkflow.setDashboardFilter(\u0027Month\u0027, e.value); \r\n                SkillsWorkflow.setDashboardFilter(\u0027startDate\u0027, firstDayOfMonth); \r\n                SkillsWorkflow.setDashboardFilter(\u0027endDate\u0027, lastDayOfMonth); \r\n\r\n                SkillsWorkflow.setDashboardFilter(\u0027FromDate\u0027, firstDayOfMonth); \r\n                SkillsWorkflow.setDashboardFilter(\u0027ToDate\u0027, lastDayOfMonth);\r\n    }\r\n}\",\r\n\r\n        \"displayFormat\": {\r\n    \"type\": \"MMMM,y\"\r\n}\r\n}",
      "DashboardDefinitionId": "98d1297b-dc86-497f-9f76-6eaf397edcb3"
    },
    {
      "Id": "4b7857c2-217e-496d-b2e5-6e4f50a2f534",
      "Name": "Calendário de Alocação",
      "Active": true,
      "UseQuery": false,
      "Query": "",
      "Size": 10,
      "Order": 5,
      "Parameters": "[{\"WidgetSubTitle\":\"Recursos do Departamento e Divis?o escolhidos, Atividades do Per?odo selecionado\",\"WidgetType\":\"resourcescheduler\",\"WidgetFilterField\":\"\",\"WidgetColor\":\"\",\"WidgetFrameStyle\":{},\"WidgetXPosition\":0,\"WidgetYPosition\":2,\"WidgetRows\":20,\"WidgetColumns\":39,\"WidgetHeader\":{\"showContextInfo\":false,\"WidgetPeriodChooser\":{\"type\":\"year\",\"visible\":false},\"WidgetMetrics\":{\"visible\":false,\"Metrics\":[{\"visible\":true,\"metricName\":\"# Forecast\",\"metricFieldValue\":\"TimeGrandTotal\"},{\"visible\":true,\"metricName\":\"# Actual\",\"metricFieldValue\":\"UtilizationPercentGrandTotal\"}]},\"showSubTitle\":false,\"showTitle\":false},\"WidgetDataSources\":{\"resources\":{\"value\":\"SELECT \\r\\n\\tssu.Oid as UserId, \\r\\n\\tssu.UserName,\\r\\n\\tut.[Name] as UserTypology,\\r\\n\\tu.HasImage as HasImage\\r\\nFROM \\r\\n\\tSecuritySystemUser ssu, \\r\\n\\t[User] u\\r\\n\\tLEFT OUTER JOIN UserTypology ut ON (ut.Oid = u.Typology)\\r\\nWHERE \\r\\n\\tssu.Oid = u.Oid AND\\r\\n\\tssu.GCRecord is null AND\\r\\n\\tssu.IsActive = 1 AND\\r\\n    (\u002700000000-0000-0000-0000-000000000000\u0027 in (@UserOid) or u.Oid in (@UserOid)) AND\\r\\n    (\u002700000000-0000-0000-0000-000000000000\u0027 in (@UserTypeOid) or ut.Oid in (@UserTypeOid))\\r\\n\\r\\n\\r\\n\\r\\n\\r\\n\\r\\n     \\r\\n \\r\\n\",\"type\":\"querytext\",\"mapping\":{\"id\":\"UserId\",\"name\":\"UserName\",\"typology\":\"UserTypology\",\"hasImage\":\"HasImage\"}},\"assignments\":{\"value\":\"select d.[Oid] AS JobId, \\r\\nd.[Number] AS JobNumber, \\r\\ne.[Subject] AS JobName, \\r\\np.[Name] as ProjectName, \\r\\nd.[EntryDateUtc] AS JobStartDate, \\r\\nd.[AgreedDateUtc] AS JobEndDate, \\r\\ndatediff(day, d.EntryDateUtc, d.AgreedDateUtc) as Duration, \\r\\nisnull(w.Color, wst.Color) as Color, \\r\\na.Oid AS AssignmentId, \\r\\na.[User] AS UserId, \\r\\na.[Workload], \\r\\ncc.[Name] as ClientName, \\r\\ncc.Oid as ClientId, \\r\\ncc.HasImage \\r\\nfrom deliverable d, Project p, CommercialClient cc, [Event] e, WorkflowState w, WorkflowStateType wst, Assignment a, AssignmentType at, [User] usr, Department dep, UserTypology ut \\r\\nwhere d.IsDraft = 0 and d.Plannable = 1 and p.Oid = d.Project and cc.Oid = d.Client and d.Oid = e.Oid \\r\\nand d.WorkflowState = w.Oid and wst.oid = w.WorkflowStateType and d.Oid = a.DocumentOid \\r\\nand a.AssignmentType = at.Oid and a.[User] = usr.Oid \\r\\nand usr.Department = dep.Oid \\r\\nand e.GCRecord is null \\r\\nand ut.Oid = usr.Typology \\r\\nand at.[Name] = \u0027Executor\u0027 \\r\\nand \\r\\n(   \\r\\n    (d.[EntryDateUtc] between @FromDate and @ToDate) OR\\r\\n    (d.[AgreedDateUtc] between @FromDate and @ToDate) OR\\r\\n    (d.[EntryDateUtc] \u003c @FromDate and d.[AgreedDateUtc] \u003e @ToDate)\\r\\n)\\r\\nand (\u002700000000-0000-0000-0000-000000000000\u0027 in (@ClientOid) or D.Client in (@ClientOid))\",\"type\":\"querytext\",\"mapping\":{\"id\":\"AssignmentId\",\"startDateUtc\":\"JobStartDate\",\"endDateUtc\":\"JobEndDate\",\"name\":\"JobName\",\"eventId\":\"JobId\",\"resourceId\":\"UserId\",\"eventColor\":\"Color\",\"workload\":\"Workload\",\"clientId\":\"ClientId\",\"clientName\":\"ClientName\",\"projectName\":\"ProjectName\",\"hasImage\":\"HasImage\"}},\"holidays\":{\"value\":\"select hol.Oid, hol.Name, hol.Date from holiday hol, division div where hol.Company = div.Company\",\"type\":\"querytext\",\"mapping\":{\"id\":\"Oid\",\"name\":\"Name\",\"startDate\":\"Date\"}},\"leaves\":{\"value\":\"select ssu.Oid as UserId, usv.Day as Date, uvt.Name as LeaveType, usv.Oid as LeaveId from SecuritySystemUser ssu, Department dep, [User] u, UserTypology ut, UserVacation usv, UserVacationType uvt, UserInfoVacation uiv where ssu.Oid = u.Oid and ssu.GCRecord is null and ssu.IsActive = 1 and u.Plannable = 1 and u.SystemAdministrator = 0 and ut.Oid = u.Typology and dep.Oid = u.Department and (exists ( select 1 from [User] u2 cross apply openjson (u.TagsJson) with (Label nvarchar(200) \u0027$.Label\u0027) where u2.Oid = u.Oid and u2.TagsJson is not null and u2.TagsJson \u003c\u003e \u0027\u0027 and isjson(u2.TagsJson) \u003e 0)) and usv.[User] = u.Oid and uiv.Oid = usv.UserInfoVacation and uvt.Oid = uiv.UserVacationType \",\"type\":\"querytext\",\"mapping\":{\"id\":\"LeaveId\",\"startDate\":\"Date\",\"name\":\"LeaveType\",\"resourceId\":\"UserId\"}},\"main\":{\"type\":\"querytext\",\"value\":\"\",\"mapping\":\"\"}},\"Filters\":{},\"QueryConfiguration\":{\"RequiredFilters\":[\"startDate\",\"endDate\",\"UserOid\",\"ClientOid\",\"UserTypeOid\"]}}]",
      "DashboardComponentType": {
        "Id": "be9c4895-90b8-4755-9054-caa7770b6a09",
        "Name": "Generic Dashboard",
        "ComponentTypeNumber": 42
      },
      "AnalyticsApiUrl": "globalQuery/RoomDashboards-Jobs/execute",
      "Configuration": "{\r\n    \"height\": 690,\r\n    \"barMargin\": 10,\r\n    \"showDailyWorkloads\": true,\r\n    \"fillTicks\": true,\r\n    \"autoAdjustTimeAxis\": false,\r\n    \"listeners\": {\r\n        \"assignmentsrefresh\": \"function(){           SW.saveComponent(this.schedulerEngine, \u0027resourceScheduler\u0027);\r\n          var setViewPreset = SW.getComponent(\u0027timePreset\u0027);\r\n          var scheduler = this.schedulerEngine;\r\n      switch(setViewPreset) {                   \r\n        case \u0027Hour\u0027:    scheduler.viewPreset = {            name: \u0027hourAndDay\u0027,            shiftUnit: \u0027day\u0027\r\n            };         break;                   \r\n        case \u0027Day\u0027:scheduler.viewPreset = {            name: \u0027weekAndDay\u0027,            shiftUnit: \u0027week\u0027\r\n            };  break;                       \r\n        case \u0027Week\u0027:scheduler.viewPreset = {            name: \u0027weekAndMonth\u0027,            shiftUnit: \u0027month\u0027\r\n            }; break;                     \r\n            case \u0027Month\u0027:scheduler.viewPreset = {            name: \u0027monthAndYear\u0027,            shiftUnit: \u0027year\u0027\r\n            };\r\n        }\r\n    }\"\r\n},\r\n\"features\": {\r\n    \"columnLines\": true,\r\n    \"eventResize\": true,\r\n    \"eventEdit\": false,\r\n    \"nonWorkingTime\": true,\r\n    \"eventDragCreate\": false,\r\n    \"headerZoom\": false,\r\n    \"filterBar\": false,\r\n    \"sort\": \"UserName\",\r\n    \"stripe\": true,\r\n    \"timeRanges\": true,\r\n    \"eventTooltip\": {\r\n        \"hoverDelay\": 2000\r\n    },\r\n    \"scheduleTooltip\": false\r\n},\r\n\"eventBodyTemplate\":\"function ({ eventRecord, assignmentRecord, showDailyWorkloads, fillTicks }) {\r\n\r\n let hasImage = !assignmentRecord || (assignmentRecord \u0026\u0026 !assignmentRecord.HasImage),\r\n eventName = eventRecord.name,\r\n eventClientId = assignmentRecord.get(\u0027clientId\u0027) || eventRecord.get(\u0027clientId\u0027),\r\n projectName = eventRecord.ProjectName || assignmentRecord.ProjectName,\r\n workload = assignmentRecord.Workload;\r\n \r\n \r\n return `\u003cdiv class=\\\"jobBodyTemplate\\\"\u003e\r\n \u003cdiv class=\\\"dashboard-component-resources\\\"\u003e\r\n \r\n \u003cdiv class=\\\"event-name-container\\\"\u003e\r\n \u003cdiv style=\\\"width: 75%\\\"\u003e\r\n \u003cdiv class=\\\"event-name\\\"\u003e${eventName}\u003c/div\u003e\r\n \u003cdiv class=\\\"project-name\\\"\u003e${projectName}\u003c/div\u003e\r\n \u003c/div\u003e\r\n \u003cdiv class=\\\"workload-container\\\"\u003e\r\n \u003cdiv style=\\\"height: 14px;\\\"\u003e\r\n \u003ci class=\\\"fal fa-clock\\\" style=\\\"color: #f44336; font-weight: 600; border-radius: 50px;font-size: 12px; background-color: white;\\\"\u003e\r\n \u003c/i\u003e\r\n \u003c/div\u003e\r\n \u003cdiv id=\\\"duration\\\"\u003e${workload}\u003c/div\u003e\r\n \u003c/div\u003e\r\n \u003c/div\u003e \r\n \u003c/div\u003e\r\n \u003cdiv style=\\\"display: flex; margin-left: -10px; width: 100%\\\"\u003e\u003c/div\u003e\r\n \u003c/div\u003e`;\r\n}\r\n \"\r\n}",
      "DashboardDefinitionId": "98d1297b-dc86-497f-9f76-6eaf397edcb3"
    },
    {
      "Id": "88881b74-7985-4de9-8ed5-c4da6cf8e983",
      "Name": "Por Alocar",
      "Active": true,
      "UseQuery": false,
      "Query": null,
      "Size": 2,
      "Order": 6,
      "Parameters": "[{\"WidgetSubTitle\":\"Atividades do Per?odo\",\"WidgetType\":\"gridbryntum\",\"WidgetFilterField\":\"\",\"WidgetColor\":\"\",\"WidgetFrameStyle\":{},\"WidgetXPosition\":39,\"WidgetYPosition\":2,\"WidgetRows\":20,\"WidgetColumns\":9,\"WidgetHeader\":{\"showContextInfo\":false,\"WidgetPeriodChooser\":{\"startDate\":\"2019-01-01\",\"endDate\":\"2019-12-31\",\"type\":\"year\",\"visible\":false},\"showSubTitle\":false,\"showTitle\":false},\"WidgetDataSources\":{\"main\":{\"type\":\"querytext\",\"value\":\"select  ws.Name,\\n        job.Oid as JobId,\\n        job.NameAndExternalId as Job,\\n        datediff(day, job.EntryDateUtc, job.AgreedDateUtc) as Duration,\\n        \u0027d\u0027 as DurationUnit,\\n        job.EntryDateUtc as StartDate,\\n        job.AgreedDateUtc as EndDate,\\n        isnull(ws.Color, wst.Color) as EventColor,\\n        job.Client as ClientId,\\n        cc.Name as ClientName,\\n        prj.Name as ProjectName,\\n        cc.HasImage,\\n        cc.Name as ClientName\\nfrom    Deliverable job, WorkflowState ws, WorkflowStateType wst, Project prj, Department dep, CommercialClient cc\\nwhere   job.WorkflowState = ws.Oid and \\n        wst.Oid = ws.WorkflowStateType and\\n        prj.Oid = job.Project and\\n        job.IsDraft = 0 and\\n        job.Plannable = 1 and\\n        cc.Oid = job.Client and\\n        not exists (\\n            select  1\\n            from    Assignment asn, AssignmentType ast\\n            where   asn.DocumentOid = job.Oid and\\n                    ast.Oid = asn.AssignmentType and\\n                    ast.[Name] = \u0027Executor\u0027\\n        ) and\\n        dep.Oid = job.Department and\\n        ws.Name not in(\u0027Canceled\u0027, \u0027Complete\u0027)\",\"mapping\":{\"id\":\"JobId\",\"name\":\"Job\",\"startDate\":\"StartDate\",\"endDate\":\"EndDate\",\"workload\":\"Duration\",\"eventColor\":\"EventColor\",\"clientId\":\"ClientId\",\"clientName\":\"clientName\",\"hasImage\":\"HasImage\"}}},\"Filters\":{},\"QueryConfiguration\":{\"RequiredFilters\":[]}}]",
      "DashboardComponentType": {
        "Id": "be9c4895-90b8-4755-9054-caa7770b6a09",
        "Name": "Generic Dashboard",
        "ComponentTypeNumber": 42
      },
      "AnalyticsApiUrl": null,
      "Configuration": "{\n    \"autoHeight\": false,\n    \"height\": 690,\n    \"rowHeight\": 50,\n    \"columns\": [\n        {\n            \"text\": \"Por Atribuir\",\n            \"headerRenderer\": \"function(data){ return `\u003cdiv style=\u0027font-weight: 700;\u0027\u003e${data.column.text}: ${data.column.grid.data.length}\u003c/div\u003e` }\",\n            \"field\": \"Name\",\n            \"htmlEncode\": false,\n            \"renderer\": \"function(data) { \n                if(data.record.HasImage)\n                {\n                    return \n                        `\u003cdiv style=\u0027width: 100%; cursor: pointer; border-radius: 4px; height: 34px; background-color: ` + \n                            data.record.EventColor + \n                            `; color: white;display: flex; justify-content: space-around; align-items: center;\u0027\u003e` +\n                            `\u003cimg style=\u0027border-radius: 20px; height: 26px;\u0027 src=\u0027` + \n                                SkillsWorkflow.getClientImages([data.record.ClientId\n                ]) + \n                            `\u0027/\u003e` +\n                            `\u003cdiv style=\u0027width: calc( 100% - 36px); display: flex; align-items: center; justify-content: space-between;\u0027\u003e` + \n                                `\u003cdiv style=\u0027width: 75%\u0027\u003e` + \n                                    `\u003cdiv style=\u0027width: 100%; margin-top: 3px; font-size: 12px; font-weight: normal; width: 100%; overflow: hidden; text-overflow: ellipsis; min-height: 17px;\u0027\u003e` +\n                                        data.record.name + \n                                    `\u003c/div\u003e` + \n                                    `\u003cdiv style=\u0027margin-top: -6px; font-size: 10px; font-weight: normal; width: 100%; overflow: hidden; text-overflow: ellipsis; font-style: italic\u0027\u003e` +\n                                        data.record.ProjectName + \n                                    `\u003c/div\u003e` +\n                                `\u003c/div\u003e` + \n                                `\u003cdiv style=\u0027width: 20%;font-size: 12px; margin: auto; text-align: right\u0027\u003e` + \n                                    `\u003cdiv style=\u0027height: 14px;\u0027\u003e` + \n                                        `\u003ci class=\u0027fal fa-clock\u0027 style=\u0027color: #f44336; font-weight: 600; border-radius: 50px;font-size: 12px; background-color: white;\u0027\u003e` +\n                                        `\u003c/i\u003e` +\n                                    `\u003c/div\u003e` + \n                                    `\u003cdiv id=\u0027duration\u0027\u003e` +\n                                        data.record.Duration +\n                                    `\u003c/div\u003e` +\n                                `\u003c/div\u003e` +\n                            `\u003c/div\u003e` +\n                        `\u003c/div\u003e`;\n            }\n                if(!data.record.HasImage)\n                {\n                    return \n                        `\u003cdiv style=\u0027width: 100%; cursor: pointer; border-radius: 4px; height: 34px; background-color: ` + \n                            data.record.EventColor + \n                            `; color: white;display: flex; justify-content: space-around; align-items: center;\u0027\u003e` +\n                            `\u003cdiv style=\u0027border-radius: 250px; overflow: hidden; width: 22px; height: 22px; border: none;\u0027\u003e` + \n                                `\u003cdiv style=\u0027color: rgb(42,\n                128,\n                185); background-color: rgb(197,\n                219,\n                243); font-size: 12px; height: 100%; line-height: 22px; display: flex; align-items: center; justify-content: center\u0027\u003e` +\n                                    `\u003cspan style=\u0027text-align: center;\u0027\u003e` + \n                                        data.record.ClientName[\n                    0\n                ] + \n                                    `\u003c/span\u003e` +\n                                `\u003c/div\u003e` +\n                            `\u003c/div\u003e` +\n                            `\u003cdiv style=\u0027width: calc( 100% - 36px); display: flex; align-items: center; justify-content: space-between;\u0027\u003e` + \n                                `\u003cdiv style=\u0027width: 75%\u0027\u003e` + \n                                    `\u003cdiv style=\u0027width: 100%; margin-top: 3px; font-size: 12px; font-weight: normal; width: 100%; overflow: hidden; text-overflow: ellipsis; min-height: 17px;\u0027\u003e` +\n                                        data.record.name + \n                                    `\u003c/div\u003e` + \n                                    `\u003cdiv style=\u0027margin-top: -6px; font-size: 10px; font-weight: normal; width: 100%; overflow: hidden; text-overflow: ellipsis; font-style: italic\u0027\u003e` +\n                                        data.record.ProjectName + \n                                    `\u003c/div\u003e` +\n                                `\u003c/div\u003e` + \n                                `\u003cdiv style=\u0027width: 20%;font-size: 12px; margin: auto; text-align: right\u0027\u003e` + \n                                    `\u003cdiv style=\u0027height: 14px;\u0027\u003e` + \n                                        `\u003ci class=\u0027fal fa-clock\u0027 style=\u0027color: #f44336; font-weight: 600; border-radius: 50px;font-size: 12px; background-color: white;\u0027\u003e` +\n                                        `\u003c/i\u003e` +\n                                    `\u003c/div\u003e` + \n                                    `\u003cdiv id=\u0027duration\u0027\u003e` +\n                                        data.record.Duration +\n                                    `\u003c/div\u003e` +\n                                `\u003c/div\u003e` +\n                            `\u003c/div\u003e` +\n                        `\u003c/div\u003e`;\n            }\n        }\"\n    }\n],\n\"listeners\": {\n    \"cellDblClick\": \"function(data){  SkillsWorkflow.preview(data.record.id, \u0027job\u0027); }\"\n},\n\"features\": {\n    \"stripe\": true,\n    \"sort\": \"name\",\n    \"cellEdit\": false\n}\n}",
      "DashboardDefinitionId": "98d1297b-dc86-497f-9f76-6eaf397edcb3"
    },
    {
      "Id": "2c46fc1b-20f1-440a-8a98-dc9d42343fdf",
      "Name": "Filtro de valores",
      "Active": true,
      "UseQuery": false,
      "Query": null,
      "Size": 10,
      "Order": 0,
      "Parameters": "[{\"WidgetSubTitle\":\"Escolha para Alocar\",\"WidgetType\":\"tag\",\"WidgetFilterField\":\"\",\"WidgetColor\":\"#ffffff\",\"WidgetFrameStyle\":{},\"WidgetXPosition\":0,\"WidgetYPosition\":0,\"WidgetRows\":2,\"WidgetColumns\":9,\"WidgetHeader\":{\"showContextInfo\":false,\"WidgetPeriodChooser\":{\"type\":\"year\",\"visible\":false},\"WidgetMetrics\":{\"visible\":false,\"Metrics\":[]},\"showSubTitle\":false,\"showTitle\":false},\"WidgetDataSources\":{\"main\":{\"type\":\"querytext\",\"value\":\"select  \u0027Resource\u0027 as GroupName, \\r\\n        \u0027UserOid\u0027 as GroupId, \\r\\n        u.Name, \\r\\n        u.Oid \\r\\nfrom    SecuritySystemUser ssu, Department dep, [User] u, UserTypology ut\\r\\nwhere   ssu.Oid = u.Oid and\\r\\n        ssu.GCRecord is null and\\r\\n        ssu.IsActive = 1 and\\r\\n        u.SystemAdministrator = 0 and\\r\\n        ut.Oid = u.Typology and\\r\\n        dep.Oid = u.Department\\r\\nunion all\\r\\nselect  \u0027User Type\u0027 as GroupName, \\r\\n        \u0027UserTypeOid\u0027 as GroupId, \\r\\n        dep.Name + \u0027 - \u0027 + ut.Name as UserType, \\r\\n        ut.Oid \\r\\nfrom    SecuritySystemUser ssu, Department dep, [User] u, UserTypology ut\\r\\nwhere   ssu.Oid = u.Oid and\\r\\n        ssu.GCRecord is null and\\r\\n        ssu.IsActive = 1 and\\r\\n        u.SystemAdministrator = 0 and\\r\\n        ut.Oid = u.Typology and\\r\\n        dep.Oid = u.Department\\r\\ngroup by dep.Name + \u0027 - \u0027 + ut.Name, ut.Oid\\r\\n\\r\\nunion all\\r\\nselect  distinct \\r\\n        \u0027Client\u0027 as GroupName, \\r\\n        \u0027ClientOid\u0027 as GroupId, \\r\\n        cc.Name, \\r\\n        cc.Oid \\r\\nfrom    deliverable d, Deliverable_UserFields duf, \\r\\n        Project p, CommercialClient cc, [Event] e, \\r\\n        WorkflowState w, WorkflowStateType wst, Assignment a, \\r\\n        AssignmentType at, [User] usr, Department dep, UserTypology ut \\r\\nwhere   d.IsDraft = 0 and\\r\\n        p.Oid = d.Project and\\r\\n        cc.Oid = d.Client and\\r\\n        d.Oid = e.Oid and\\r\\n        d.WorkflowState = w.Oid and\\r\\n        wst.oid = w.WorkflowStateType and\\r\\n        d.Oid = a.DocumentOid and\\r\\n        a.AssignmentType = at.Oid and\\r\\n        a.[User] = usr.Oid and\\r\\n        usr.Department = dep.Oid and\\r\\n        e.GCRecord is null and\\r\\n        ut.Oid = usr.Typology and\\r\\n        at.[Name] = \u0027Executor\u0027 and\\r\\n        duf.Oid = d.Oid\",\"mapping\":{\"groupExpr\":\"GroupName\",\"groupId\":\"GroupId\",\"displayExpr\":\"Name\",\"valueExpr\":\"Oid\"}}},\"Filters\":{},\"QueryConfiguration\":{}}]",
      "DashboardComponentType": {
        "Id": "be9c4895-90b8-4755-9054-caa7770b6a09",
        "Name": "Generic Dashboard",
        "ComponentTypeNumber": 42
      },
      "AnalyticsApiUrl": null,
      "Configuration": "{\n    \"width\": \"100%\"\n}",
      "DashboardDefinitionId": "98d1297b-dc86-497f-9f76-6eaf397edcb3"
    },
    {
      "Id": "dbf8d73e-f3bd-438c-85b7-ffebcc3f4d96",
      "Name": "Selector de datas",
      "Active": true,
      "UseQuery": false,
      "Query": null,
      "Size": 2,
      "Order": 0,
      "Parameters": "[{\"WidgetSubTitle\":\"\",\"WidgetType\":\"selectbox\",\"WidgetFilterField\":\"\",\"WidgetColor\":\"#ffffff\",\"WidgetFrameStyle\":{},\"WidgetXPosition\":31,\"WidgetYPosition\":0,\"WidgetRows\":2,\"WidgetColumns\":7,\"WidgetHeader\":{\"showContextInfo\":false,\"WidgetPeriodChooser\":{\"type\":\"year\",\"visible\":false},\"WidgetMetrics\":{\"visible\":false,\"Metrics\":[]},\"showSubTitle\":false,\"showTitle\":false},\"WidgetDataSources\":{\"main\":{\"type\":\"queryempty\",\"value\":\"\",\"mapping\":\"\"}},\"Filters\":{},\"QueryConfiguration\":{}}]",
      "DashboardComponentType": {
        "Id": "be9c4895-90b8-4755-9054-caa7770b6a09",
        "Name": "Generic Dashboard",
        "ComponentTypeNumber": 42
      },
      "AnalyticsApiUrl": null,
      "Configuration": "{\n    \"dataSource\": [\n        \"Hour\",\n        \"Day\"\n    ],\n    \"value\": \"Day\",\n    \"onValueChanged\": \"function(e){debugger;          var range = SW.getComponent(\u0027Range\u0027);                                      SW.saveComponent(e.value, \u0027timePreset\u0027);                   var scheduler = SW.getComponent(\u0027resourceScheduler\u0027);                                                       switch(e.value) {                                                                        case \u0027Hour\u0027:              var unit = \u0027day\u0027;           scheduler.viewPreset = {            name: \u0027hourAndDay\u0027,            shiftUnit: unit        };         break;                                                                 case \u0027Day\u0027:                 var unit = \u0027week\u0027;                   scheduler.viewPreset = {            name: \u0027weekAndDay\u0027,            shiftUnit: unit        };  break;                     case \u0027Week\u0027:                var unit = \u0027month\u0027;                 scheduler.viewPreset = {            name: \u0027weekAndMonth\u0027,            shiftUnit: unit        };break;                                       case \u0027Month\u0027:                 var unit = \u0027year\u0027;            scheduler.viewPreset = {            name: \u0027monthAndYear\u0027,            shiftUnit: unit        };               }                  }\"\n}",
      "DashboardDefinitionId": "98d1297b-dc86-497f-9f76-6eaf397edcb3"
    }
  ],
  "QueryText": "",
  "UseStore": false,
  "StoreEntity": null,
  "Version": 2,
  "Default": false
}
