{
  "DashboardDefinitionRoles": [],
  "Id": "496672c6-5fd0-4291-a32f-3690dfdd5e88",
  "Name": "Status Dashboard",
  "Active": true,
  "Location": 1,
  "DocumentId": "d1650714-7d21-4368-994e-d9c951981825",
  "DocumentName": "Project",
  "DocumentsConfiguration": "{\"entity\":\"\",\"operations\":{\"read\":{\"endpoint\":\"\"},\"update\":{\"endpoint\":\"\",\"model\":{}},\"create\":{\"endpoint\":\"\",\"model\":{}},\"patch\":{\"endpoint\":\"\",\"model\":[{\"field\":\"\",\"caption\":\"\",\"type\":\"\"}]},\"remove\":{\"endpoint\":\"\"},\"lookup\":{\"endpoint\":\"\"},\"lookupById\":{\"endpoint\":\"\"}},\"layout\":{\"create\":{},\"read\":{},\"patch\":{}},\"customDocument\":{\"useCustomStyle\":false,\"mainColor\":\"\",\"secondaryColor\":\"\",\"imageClass\":\"\",\"namePlural\":\"\",\"name\":\"\",\"systemName\":\"\"},\"availableOptions\":{\"feed\":false,\"info\":true,\"files\":false,\"userfields\":false,\"dashboard\":false}}",
  "Templates": [],
  "DashboardDefinitionComponents": [
    {
      "Id": "24cb0f86-9b20-4b8e-9309-0561615a48f3",
      "Name": "User Burn",
      "Active": true,
      "UseQuery": false,
      "Query": null,
      "Size": 4,
      "Order": 5,
      "Parameters": "[{\"WidgetSubTitle\":\"Actual Time\",\"WidgetType\":\"chart\",\"WidgetFilterField\":\"\",\"WidgetColor\":\"#efefef\",\"WidgetHeight\":300,\"WidgetHeader\":{\"showContextInfo\":false,\"WidgetPeriodChooser\":{\"type\":\"year\",\"visible\":false},\"WidgetMetrics\":{\"visible\":true,\"Metrics\":[{\"visible\":true,\"metricName\":\"Billable Time\",\"metricFieldValue\":\"TotalBillableTime\"},{\"visible\":true,\"metricName\":\"Non-billable Time\",\"metricFieldValue\":\"TotalNonBillableTime\"}]},\"showSubTitle\":true,\"showTitle\":true},\"WidgetDataSources\":{\"main\":{\"type\":\"querytext\",\"value\":\"select  *,\\r\\n        sum(BillableTime) over() as TotalBillableTime,\\r\\n        sum(NonBillableTime) over() as TotalNonBillableTime\\r\\nfrom    (\\r\\n        select  [User],\\r\\n                sum(ContractedTime) as ContractedTime,\\r\\n                sum(BillableTime) as BillableTime,\\r\\n                sum(NonBillableTime) as NonBillableTime\\r\\n        from    (\\r\\n                select  usr.Name as [User],\\r\\n                        edt.Hours as ContractedTime,\\r\\n                        0 as BillableTime,\\r\\n                        0 as NonBillableTime\\r\\n                from    Estimate est, EstimateItem eit, Contract cnt,\\r\\n                        EstimateItemDetail edt left outer join [User] usr on usr.Oid = edt.[User]\\r\\n                where   est.Contract = cnt.Oid and\\r\\n                        eit.Estimate = est.Oid and\\r\\n                        edt.EstimateItem = eit.Oid and\\r\\n                        edt.Type = 2\\r\\n                        /*[ProjectFilter]*/ and cnt.Oid = (select [Contract] from Project where Oid = @ProjectId) /*[/ProjectFilter]*/\\r\\n                union all\\r\\n                select  usr.Name as [User],\\r\\n                        0 as ContractedTime,\\r\\n                        iif(tim.Billable = 1 or tim.Billable is null, DurationHours + DurationMinutes / 60.0, 0) as Billabletime,\\r\\n                        iif(tim.Billable = 1 or tim.Billable is null, 0, DurationHours + DurationMinutes / 60.0) as NonBillabletime\\r\\n                from    Timesheet tim, Project prj, Contract cnt, [User] usr\\r\\n                where   tim.Project = prj.Oid and \\r\\n                        prj.Contract = cnt.Oid and\\r\\n                        usr.Oid = tim.CreatedBy\\r\\n                        /*[ProjectFilter]*/ and prj.Oid = @ProjectId /*[/ProjectFilter]*/\\r\\n                ) t\\r\\n        group by [User]\\r\\n        ) t\"}},\"Filters\":{},\"QueryConfiguration\":{\"PreviousPeriod\":{\"Show\":false,\"KeyFieldName\":\"\",\"Type\":0},\"RequiredFilters\":[]}}]",
      "DashboardComponentType": {
        "Id": "7831bc23-b74a-48b2-95a7-130d290fd43b",
        "Name": "Generic Dashboard",
        "ComponentTypeNumber": 42
      },
      "AnalyticsApiUrl": "globalQuery/Contract - Resources - Users/execute",
      "Configuration": "{\n  \"commonSeriesSettings\": {\n    \"argumentField\": \"User\",\n    \"type\": \"stackedbar\"\n  },\n  \"argumentAxis\": {\n    \"label\": {\n      \"font\": {\n        \"size\": 8,\n        \"family\": \"Varela Round\"\n      }\n    }\n  },\n  \"valueAxis\": {\n    \"label\": {\n      \"font\": {\n        \"family\": \"Varela Round\"\n      }\n    }\n  },\n  \"series\": [\n    {\n      \"valueField\": \"BillableTime\",\n      \"name\": \"Billable Time\"\n    },\n    {\n      \"valueField\": \"NonBillableTime\",\n      \"name\": \"Non-billable Time\"\n    }\n  ],\n  \"size\": {\n    \"height\": 250\n  },\n  \"rotated\": true\n}",
      "DashboardDefinitionId": "496672c6-5fd0-4291-a32f-3690dfdd5e88"
    },
    {
      "Id": "462517aa-8ff8-4652-b7b4-14dade4ac09c",
      "Name": "Typology Group Burn",
      "Active": true,
      "UseQuery": false,
      "Query": null,
      "Size": 8,
      "Order": 4,
      "Parameters": "[{\"WidgetSubTitle\":\"Actual Time\",\"WidgetType\":\"chart\",\"WidgetFilterField\":\"\",\"WidgetColor\":\"#efefef\",\"WidgetHeight\":300,\"WidgetHeader\":{\"showContextInfo\":false,\"WidgetPeriodChooser\":{\"type\":\"year\",\"visible\":false},\"WidgetMetrics\":{\"visible\":true,\"Metrics\":[{\"visible\":true,\"metricName\":\"Contracted Time\",\"metricFieldValue\":\"TotalContractedTime\"},{\"visible\":true,\"metricName\":\"Planned Time\",\"metricFieldValue\":\"TotalPlannedTime\"},{\"visible\":true,\"metricName\":\"Actual Time\",\"metricFieldValue\":\"TotalActualTime\"}]},\"showSubTitle\":true,\"showTitle\":true},\"WidgetDataSources\":{\"main\":{\"type\":\"querytext\",\"value\":\"select  *,\\r\\n        sum(ContractedTime) over() as TotalContractedTime,\\r\\n        sum(PlannedTime) over() as TotalPlannedTime,\\r\\n        sum(ActualTime) over() as TotalActualTime\\r\\nfrom    (\\r\\n        select  TypologyGroup,\\r\\n                sum(ContractedTime) as ContractedTime,\\r\\n                sum(PlannedTime) as PlannedTime,\\r\\n                sum(ActualTime) as ActualTime\\r\\n        from    (\\r\\n                        select  utg.Name as TypologyGroup,\\r\\n                                edt.Hours * eit.Retainer as ContractedTime,\\r\\n                                0 as PlannedTime,\\r\\n                                0 as ActualTime\\r\\n                        from    Estimate est, EstimateItem eit, Contract cnt, EstimateItemDetail edt, UserTypologyGroup utg\\r\\n                        where   est.Contract = cnt.Oid and\\r\\n                                eit.Estimate = est.Oid and\\r\\n                                edt.EstimateItem = eit.Oid and\\r\\n                                utg.Oid = edt.UserTypologyGroup and\\r\\n                                edt.Type = 2\\r\\n                                /*[ProjectFilter]*/ and cnt.Oid = (select [Contract] from Project where Oid = @ProjectId) /*[/ProjectFilter]*/\\r\\n                        union all\\r\\n                        select  utg.Name as TypologyGroup,\\r\\n                                0 as ContractedTime,\\r\\n                                pht.PlannedMinutes / 60.0 as PlannedTime,\\r\\n                                0 as ActualTime\\r\\n                        from    PlannedHoursTotal pht, Project prj, Contract cnt, UserTypologyGroup utg\\r\\n                        where   prj.Oid = pht.Project and\\r\\n                                prj.Contract = cnt.Oid and\\r\\n                                utg.Oid = pht.UserTypologyGroup and\\r\\n                                pht.GCRecord is null \\r\\n                                /*[ProjectFilter]*/ and prj.Oid = @ProjectId /*[/ProjectFilter]*/\\r\\n                        union all\\r\\n                        select  utg.Name as TypologyGroup,\\r\\n                                0 as ContractedTime,\\r\\n                                0 as PlannedTime,\\r\\n                                DurationHours + DurationMinutes / 60.0 as ActualTime\\r\\n                        from    Timesheet tim, Project prj, Contract cnt, [User] usr, UserTypology ust, UserTypologyGroup utg\\r\\n                        where   tim.Project = prj.Oid and \\r\\n                                prj.Contract = cnt.Oid and\\r\\n                                usr.Oid = tim.CreatedBy and\\r\\n                                ust.Oid = usr.Typology and\\r\\n                                utg.Oid = ust.UserTypologyGroup\\r\\n                                /*[ProjectFilter]*/ and prj.Oid = @ProjectId /*[/ProjectFilter]*/\\r\\n                ) t\\r\\n        group by TypologyGroup\\r\\n        ) t\"}},\"Filters\":{},\"QueryConfiguration\":{\"PreviousPeriod\":{\"Show\":false,\"KeyFieldName\":\"\",\"Type\":0},\"RequiredFilters\":[]}}]",
      "DashboardComponentType": {
        "Id": "7831bc23-b74a-48b2-95a7-130d290fd43b",
        "Name": "Generic Dashboard",
        "ComponentTypeNumber": 42
      },
      "AnalyticsApiUrl": "globalQuery/Contract - Resources - Typology Group/execute",
      "Configuration": "{\n  \"commonSeriesSettings\": {\n    \"argumentField\": \"TypologyGroup\"\n  },\n  \"argumentAxis\": {\n    \"label\": {\n      \"font\": {\n        \"size\": 8,\n        \"family\": \"Varela Round\"\n      }\n    }\n  },\n  \"valueAxis\": {\n    \"label\": {\n      \"font\": {\n        \"family\": \"Varela Round\"\n      }\n    }\n  },\n  \"series\": [\n    {\n      \"type\": \"area\",\n      \"valueField\": \"PlannedTime\",\n      \"name\": \"Planned Time\"\n    },\n    {\n      \"type\": \"bar\",\n      \"valueField\": \"ActualTime\",\n      \"name\": \"Actual Time\"\n    },\n    {\n      \"type\": \"line\",\n      \"valueField\": \"ContractedTime\",\n      \"name\": \"Contracted Time\",\n      \"point\": {\n    \"symbol\": \"triangleDown\",\n        \"color\":\"#a5bdd7\"\n      }\n    }\n  ],\n  \"size\": {\n    \"height\": 250\n  },\n  \"legend\": {\n    \"visible\": true,\n    \"orientation\":\"horizontal\",\n    \"verticalAlignment\":\"bottom\",\n    \"horizontalAlignment\":\"center\",\n    \"font\": {\n      \"family\": \"Varela Round\"\n    }\n  }\n}",
      "DashboardDefinitionId": "496672c6-5fd0-4291-a32f-3690dfdd5e88"
    },
    {
      "Id": "95477b6a-3c7a-4101-84dd-6dc05e51a63e",
      "Name": "Typology Group Contribution",
      "Active": true,
      "UseQuery": false,
      "Query": null,
      "Size": 4,
      "Order": 3,
      "Parameters": "[{\"WidgetSubTitle\":\"Utilization\",\"WidgetType\":\"pie\",\"WidgetFilterField\":\"\",\"WidgetColor\":\"#efefef\",\"WidgetHeight\":300,\"WidgetHeader\":{\"showContextInfo\":false,\"WidgetPeriodChooser\":{\"type\":\"year\",\"visible\":false},\"WidgetMetrics\":{\"visible\":true,\"Metrics\":[{\"visible\":true,\"metricName\":\"# Actual\",\"metricFieldValue\":\"BillableHoursGrandTotal\"},{\"visible\":true,\"metricName\":\"# Planned\",\"metricFieldValue\":\"PlannedHoursGrandTotal\"},{\"visible\":true,\"metricName\":\"# Contracted\",\"metricFieldValue\":\"ContractedHoursGrandTotal\"}]},\"showSubTitle\":true,\"showTitle\":true},\"WidgetDataSources\":{\"main\":{\"type\":\"querytext\",\"value\":\"SELECT\\r\\n    v.[TypologyGroup],\\r\\n\\tsum(v.[ActualHours]) as [ActualHours],\\r\\n    sum(v.[BillableHours]) as BillableHours,\\r\\n    sum(v.BillableHoursIncome) as BillableHoursIncome,\\r\\n\\tsum(v.ContractedHours) as ContractedHours,\\r\\n\\tsum(v.PlannedHours) as PlannedHours,\\r\\n\\tIIF(sum(v.ContractedHours) \u003e 0, sum(v.BillableHours) / sum(v.ContractedHours), 0.0) as ActualContractedPercentage,\\r\\n\\tIIF(sum(v.PlannedHours) \u003e 0, sum(v.BillableHours) / sum(v.PlannedHours), 0.0) as ActualPlannedPercentage,\\r\\n\\tsum(sum(v.[BillableHours])) OVER () as BillableHoursGrandTotal,\\r\\n    sum(sum(v.[PlannedHours])) OVER () as PlannedHoursGrandTotal,\\r\\n    sum(sum(v.[ContractedHours])) OVER () as ContractedHoursGrandTotal\\r\\nFROM  \\r\\n(\\r\\n\\tSELECT\\r\\n\\t\\tutg.[Name] as [TypologyGroup],\\r\\n\\t\\t0 as [ActualHours],\\r\\n\\t\\t0 as BillableHours,\\r\\n\\t\\t0 as BillableHoursIncome,\\r\\n\\t\\tsum(eid.[Hours]) as ContractedHours,\\r\\n\\t\\t0 as PlannedHours\\r\\n\\tFROM   \\r\\n\\t\\tdbo.Estimate e,\\r\\n\\t\\tdbo.EstimateItem ei,\\r\\n\\t\\tdbo.EstimateItemDetail eid,\\r\\n\\t\\tdbo.UserTypologyGroup utg\\r\\n\\tWHERE\\r\\n\\t\\te.[Contract] = (SELECT [Contract] FROM Project WHERE Oid = @ProjectId)\\r\\n\\t\\tAND ei.Estimate = e.Oid\\r\\n\\t\\tAND eid.EstimateItem = ei.Oid AND eid.[Type] = 2\\r\\n\\t\\tAND utg.Oid = eid.UserTypologyGroup\\r\\n\\tGROUP BY \\r\\n\\t\\tutg.[Name]\\r\\n\\tUNION ALL\\r\\n\\tSELECT\\r\\n\\t\\tt.[TypologyGroup],\\r\\n\\t\\tsum(t.[Hours]) as [ActualHours],\\r\\n\\t\\tsum((t.[Hours] - (t.NewBusinessHours + t.AdministrativeHours))) as BillableHours,\\r\\n\\t\\tsum((t.[Hours] - (t.NewBusinessHours + t.AdministrativeHours)) * ISNULL(eid.UnitPriceIncome, 0)) as BillableHoursIncome,\\r\\n\\t\\t0 as ContractedHours,\\r\\n\\t\\t0 as PlannedHours\\r\\n\\tFROM   \\r\\n\\t\\tdbo.SkillAnalyticsTimeUtilization t\\r\\n\\t\\tLEFT OUTER JOIN dbo.Estimate e ON (e.[Contract] = (SELECT [Contract] FROM Project WHERE Oid = @ProjectId))\\r\\n\\t\\tLEFT OUTER JOIN dbo.EstimateItem ei on (ei.Estimate = e.Oid)\\r\\n\\t\\tLEFT OUTER JOIN dbo.EstimateItemDetail eid on (eid.EstimateItem = ei.Oid AND eid.[Type] = 2 AND (eid.Department = t.DepartmentId AND eid.UserTypologyGroup = t.TypologyGroupId))\\r\\n\\tWHERE\\r\\n\\t\\tt.[TypologyGroup] IS NOT NULL\\r\\n\\t\\t/*[/ProjectFilter]*/ and t.ProjectId = @ProjectId /*[/ProjectFilter]*/\\r\\n\\tGROUP BY \\r\\n\\t\\tt.[TypologyGroup]\\r\\n\\tUNION ALL\\r\\n\\tSELECT\\r\\n\\t\\tISNULL(utgp.[Name], utg.[Name]) as [TypologyGroup],\\r\\n\\t\\t0 as [ActualHours],\\r\\n\\t\\t0 as BillableHours,\\r\\n\\t\\t0 as BillableHoursIncome,\\r\\n\\t\\t0 as ContractedHours,\\r\\n\\t\\tSUM((ISNULL(pht.PlannedMinutes, 0) / 60.0)) as PlannedHours\\r\\n\\tFROM   \\r\\n\\t\\tdbo.PlannedHoursTotal pht\\r\\n\\t\\tLEFT OUTER JOIN [User] u ON (u.Oid = pht.[User])\\r\\n\\t\\tLEFT OUTER JOIN [UserTypology] ut ON (ut.Oid = u.Typology)\\r\\n\\t\\tLEFT OUTER JOIN [UserTypologyGroup] utg ON (utg.Oid = ut.UserTypologyGroup)\\r\\n\\t\\tLEFT OUTER JOIN [UserTypologyGroup] utgp ON (utgp.Oid = pht.UserTypologyGroup),\\r\\n\\t\\tdbo.Project p\\r\\n\\tWHERE\\r\\n\\t\\tpht.GCRecord is null\\r\\n\\t\\tAND p.Oid = pht.Project\\r\\n\\t\\t/*[/ProjectFilter]*/ and p.Oid = @ProjectId /*[/ProjectFilter]*/\\r\\n\\tGROUP BY \\r\\n\\t\\tISNULL(utgp.[Name], utg.[Name])\\r\\n) v\\r\\nGROUP BY\\r\\n\\tv.TypologyGroup\"}},\"Filters\":{},\"QueryConfiguration\":{\"PreviousPeriod\":{\"Show\":false,\"KeyFieldName\":\"\",\"Type\":0},\"RequiredFilters\":[]}}]",
      "DashboardComponentType": {
        "Id": "7831bc23-b74a-48b2-95a7-130d290fd43b",
        "Name": "Generic Dashboard",
        "ComponentTypeNumber": 42
      },
      "AnalyticsApiUrl": "globalQuery/Analytics_Contracts_Per_TypologyGroup/execute",
      "Configuration": "{\n  \"type\": \"doughnut\",\n  \"series\": {\n    \"argumentField\": \"TypologyGroup\",\n    \"valueField\": \"BillableHours\",\n    \"label\": {\n      \"visible\": false,\n      \"format\": \"fixedPoint\",\n      \"connector\": {\n        \"visible\": true,\n        \"width\": 1\n      }\n    },\n    \"smallValuesGrouping\": {\n                \"mode\": \"topN\",\n                \"topCount\": 10\n            }\n  },\n  \"size\": {\n    \"height\": 250\n  },\n  \"legend\": {\n    \"visible\":true,\n    \"horizontalAlignment\": \"left\",\n    \"verticalAlignment\": \"middle\",\n    \"itemTextPosition\" : \"right\",\n    \"paddingLeftRight\" : 0,\n    \"font\": {\n      \"size\": 8,\n      \"family\": \"Varela Round\"\n    }\n  }\n}",
      "DashboardDefinitionId": "496672c6-5fd0-4291-a32f-3690dfdd5e88"
    },
    {
      "Id": "44b8e63a-24ab-4586-b8ae-b8fe37f224b8",
      "Name": "Summary",
      "Active": true,
      "UseQuery": false,
      "Query": null,
      "Size": 12,
      "Order": 1,
      "Parameters": "[{\"WidgetSubTitle\":\"Time per Department and Typology Group\",\"WidgetType\":\"grid\",\"WidgetFilterField\":\"\",\"WidgetColor\":\"\",\"WidgetHeight\":\"300\",\"WidgetHeader\":{\"showContextInfo\":false,\"WidgetPeriodChooser\":{\"type\":\"year\",\"visible\":false},\"WidgetMetrics\":{\"visible\":true,\"Metrics\":[{\"visible\":true,\"metricName\":\"# Actual\",\"metricFieldValue\":\"BillableHoursGrandTotal\"},{\"visible\":true,\"metricName\":\"# Planned\",\"metricFieldValue\":\"PlannedHoursGrandTotal\"},{\"visible\":true,\"metricName\":\"# Contracted\",\"metricFieldValue\":\"ContractedHoursGrandTotal\"},{\"visible\":true,\"metricName\":\"% Burn\",\"metricFieldValue\":\"ActualContractedPercentageGrandTotal\"}]},\"showSubTitle\":true,\"showTitle\":true},\"WidgetDataSources\":{\"main\":{\"type\":\"querytext\",\"value\":\"SELECT\\r\\n\\tv.[Department],\\t\\t\\t\\t\\t\\t\\t\\t\\r\\n    v.[TypologyGroup],\\r\\n\\tsum(v.[ActualHours]) as [ActualHours],\\r\\n    sum(v.ActualHoursCost) as ActualHoursCost,\\r\\n\\tsum(v.ActualHoursIncome) as ActualHoursIncome,\\r\\n    sum(v.[BillableHours]) as BillableHours,\\r\\n    sum(v.BillableHoursIncome) as BillableHoursIncome,\\r\\n\\tsum(v.ContractedHours) as ContractedHours,\\r\\n\\tsum(v.ContractedHoursIncome) as ContractedHoursIncome,\\r\\n\\tsum(v.PlannedHours) as PlannedHours,\\r\\n\\tsum(v.PlannedHoursIncome) as PlannedHoursIncome,\\r\\n\\t(sum(v.ContractedHoursIncome) - sum(v.ActualHoursCost)) as ContractedActualIncomeVariation,\\r\\n\\tIIF(sum(v.ContractedHours) \u003e 0, sum(v.BillableHours) / sum(v.ContractedHours), 0.0) as ActualContractedPercentage,\\r\\n\\tIIF(sum(v.PlannedHours) \u003e 0, sum(v.BillableHours) / sum(v.PlannedHours), 0.0) as ActualPlannedPercentage,\\r\\n\\tsum(sum(v.[BillableHours])) OVER () as BillableHoursGrandTotal,\\r\\n    sum(sum(v.[PlannedHours])) OVER () as PlannedHoursGrandTotal,\\r\\n    sum(sum(v.[ContractedHours])) OVER () as ContractedHoursGrandTotal,\\r\\n\\tIIF(sum(sum(v.[ContractedHours])) OVER () \u003e 0, sum(sum(v.[BillableHours])) OVER () / sum(sum(v.[ContractedHours])) OVER (), 0.0) as ActualContractedPercentageGrandTotal\\r\\nFROM  \\r\\n(\\r\\n\\tSELECT\\r\\n\\t\\tdp.[Name] as [Department],\\t\\t\\t\\t\\t\\t\\t\\t\\r\\n\\t\\tutg.[Name] as [TypologyGroup],\\r\\n\\t\\t0 as [ActualHours],\\r\\n\\t\\t0 as ActualHoursCost,\\r\\n\\t\\t0 as ActualHoursIncome,\\r\\n\\t\\t0 as BillableHours,\\r\\n\\t\\t0 as BillableHoursIncome,\\r\\n\\t\\tsum(eid.[Hours]) as ContractedHours,\\r\\n\\t\\tsum(eid.[Hours] * ISNULL(eid.UnitPriceIncome, 0)) as ContractedHoursIncome,\\r\\n\\t\\t0 as PlannedHours,\\r\\n\\t\\t0 as PlannedHoursIncome\\r\\n\\tFROM   \\r\\n\\t\\tdbo.Estimate e,\\r\\n\\t\\tdbo.EstimateItem ei,\\r\\n\\t\\tdbo.EstimateItemDetail eid,\\r\\n\\t\\tdbo.Department dp,\\r\\n\\t\\tdbo.UserTypologyGroup utg\\r\\n\\tWHERE\\r\\n\\t\\te.[Contract] = (select [Contract] from Project where Oid = @ProjectId)\\r\\n\\t\\tAND ei.Estimate = e.Oid\\r\\n\\t\\tAND eid.EstimateItem = ei.Oid AND eid.[Type] = 2\\r\\n\\t\\tAND dp.Oid = eid.Department\\r\\n\\t\\tAND utg.Oid = eid.UserTypologyGroup\\r\\n\\tGROUP BY \\r\\n\\t\\tdp.[Name],\\r\\n\\t\\tutg.[Name]\\r\\n\\tUNION ALL\\r\\n\\tSELECT\\r\\n\\t\\tt.[Department] as [Department],\\t\\t\\t\\t\\t\\t\\t\\t\\r\\n\\t\\tt.[TypologyGroup],\\r\\n\\t\\tsum(t.[Hours]) as [ActualHours],\\r\\n\\t\\tsum(ISNULL(t.TotalUserCost, 0)) as ActualHoursCost,\\r\\n\\t\\tsum(t.[Hours] * ISNULL(eid.UnitPriceIncome, 0)) as ActualHoursIncome,\\r\\n\\t\\tsum((t.[Hours] - (t.NewBusinessHours + t.AdministrativeHours))) as BillableHours,\\r\\n\\t\\tsum((t.[Hours] - (t.NewBusinessHours + t.AdministrativeHours)) * ISNULL(eid.UnitPriceIncome, 0)) as BillableHoursIncome,\\r\\n\\t\\t0 as ContractedHours,\\r\\n\\t\\t0 as ContractedHoursIncome,\\r\\n\\t\\t0 as PlannedHours,\\r\\n\\t\\t0 as PlannedHoursIncome\\r\\n\\tFROM   \\r\\n\\t\\t(\\r\\n\\t\\t\\tselect \\r\\n\\t\\t\\t\\tt.UserDepartmentId as DepartmentId,\\r\\n\\t\\t\\t\\tt.Department,\\r\\n\\t\\t\\t\\tutg.Oid as TypologyGroupId,\\r\\n\\t\\t\\t\\tp.[Contract] as ProjectContractId,\\r\\n\\t\\t\\t\\tutg.[Name] as TypologyGroup,\\r\\n\\t\\t\\t    iif(t.IsAdministrative = 1, t.[Hours], 0) as AdministrativeHours,\\r\\n\\t\\t\\t    IIF(\\r\\n\\t\\t\\t\\t\\t(\\r\\n\\t\\t\\t\\t\\t\\tcase \\r\\n\\t\\t\\t\\t\\t\\t\\twhen t.IsAdministrative = 0 and \\r\\n\\t\\t\\t\\t\\t\\t\\t(\\r\\n\\t\\t\\t\\t\\t\\t\\t\\tisnull(jc.Billable, 0) = 0 and \\r\\n\\t\\t\\t\\t\\t\\t\\t\\tisnull(pc.Billable, 0) = 0\\r\\n\\t\\t\\t\\t\\t\\t\\t)\\r\\n\\t\\t\\t\\t\\t\\t\\tthen 1 \\r\\n\\t\\t\\t\\t\\t\\t\\telse 0 \\r\\n\\t\\t\\t\\t\\t\\tend\\r\\n\\t\\t\\t\\t\\t) = 1, t.[Hours], 0\\r\\n\\t\\t\\t\\t) as NewBusinessHours,\\r\\n\\t\\t\\t    IIF(\\r\\n\\t\\t\\t    (\\r\\n\\t\\t\\t\\t    case \\r\\n\\t\\t\\t\\t\\t    when t.IsAdministrative = 0 and \\r\\n\\t\\t\\t\\t\\t    (\\r\\n\\t\\t\\t\\t\\t\\t    (pc.Billable = 1 and isnull(jc.Billable, 0) = 0)\\r\\n\\t\\t\\t\\t\\t    ) \\r\\n\\t\\t\\t\\t\\t    then (t.[Hours] / 60.0) \\r\\n\\t\\t\\t\\t\\t    else 0 \\r\\n\\t\\t\\t\\t    end\\r\\n\\t\\t\\t\\t\\t) = 1, t.[Hours], 0\\r\\n\\t\\t\\t\\t) as InternalWorkHours,\\r\\n\\t\\t\\t    IIF(\\r\\n\\t\\t\\t    (\\r\\n\\t\\t\\t\\t    case\\r\\n\\t\\t\\t\\t\\t    when t.IsAdministrative = 0 and \\r\\n\\t\\t\\t\\t\\t    (\\r\\n\\t\\t\\t\\t\\t\\t    (pc.Billable = 1 or jc.Billable = 1)\\r\\n\\t\\t\\t\\t\\t    )\\r\\n\\t\\t\\t\\t\\t    then (t.[Hours] / 60.0) \\r\\n\\t\\t\\t\\t\\t    else 0 \\r\\n\\t\\t\\t\\t    end\\r\\n\\t\\t\\t\\t\\t) = 1, t.[Hours], 0\\r\\n\\t\\t\\t    ) as BillableHours,\\r\\n\\t\\t\\t    (t.[Hours] / 60.0) as [Hours],\\r\\n\\t\\t\\t\\tt.TotalUserCost\\r\\n\\t\\t\\tfrom\\tdbo.SkillTimesheetExpanded t\\r\\n\\t\\t\\t\\t\\tinner join Project p ON (p.Oid = t.ProjectId AND p.Oid = @ProjectId)\\r\\n\\t\\t\\t\\t\\tleft outer join ProjectClassification pc on (pc.Oid = p.Classification)\\r\\n\\t\\t\\t\\t\\tleft outer join Deliverable d on (d.Oid = t.DeliverableId)\\r\\n\\t\\t\\t        left outer join JobClassification jc on (jc.Oid = d.Classification)\\r\\n\\t\\t\\t\\t\\tleft outer join UserTypology tp on (tp.Oid = t.UserTypologyId)\\r\\n\\t\\t            left outer join UserTypologyGroup utg on (utg.Oid = tp.UserTypologyGroup)\\r\\n\\t\\t) t\\r\\n\\t\\tLEFT OUTER JOIN dbo.Estimate e ON (e.[Contract] = (select [Contract] from Project where Oid = @ProjectId))\\r\\n\\t\\tLEFT OUTER JOIN dbo.EstimateItem ei on (ei.Estimate = e.Oid)\\r\\n\\t\\tLEFT OUTER JOIN dbo.EstimateItemDetail eid on (eid.EstimateItem = ei.Oid AND eid.[Type] = 2 AND (eid.Department = t.DepartmentId AND eid.UserTypologyGroup = t.TypologyGroupId))\\r\\n\\tWHERE\\r\\n\\t\\tt.[Department] IS NOT NULL\\r\\n\\t\\tAND t.[TypologyGroup] IS NOT NULL\\r\\n\\t\\t/*[/ProjectFilter]*/ and t.ProjectContractId = (select [Contract] from Project where Oid = @ProjectId) /*[/ProjectFilter]*/\\r\\n\\tGROUP BY \\r\\n\\t\\tt.[Department],\\r\\n\\t\\tt.[TypologyGroup]\\r\\n\\tUNION ALL\\r\\n\\tSELECT\\r\\n\\t\\tISNULL(utdp.[Name], utgdp.[Name]) as [Department],\\t\\t\\t\\t\\t\\t\\t\\t\\r\\n\\t\\tISNULL(utgp.[Name], utg.[Name]) as [TypologyGroup],\\r\\n\\t\\t0 as [ActualHours],\\r\\n\\t\\t0 as ActualHoursCost,\\r\\n\\t\\t0 as ActualHoursIncome,\\r\\n\\t\\t0 as BillableHours,\\r\\n\\t\\t0 as BillableHoursIncome,\\r\\n\\t\\t0 as ContractedHours,\\r\\n\\t\\t0 as ContractedHoursIncome,\\r\\n\\t\\tSUM((ISNULL(pht.PlannedMinutes, 0) / 60.0)) as PlannedHours,\\r\\n\\t\\tSUM((ISNULL(pht.PlannedMinutes, 0) / 60.0) * ISNULL(eid.UnitPriceIncome, 0)) as PlannedHoursIncome\\r\\n\\tFROM   \\r\\n\\t\\tdbo.PlannedHoursTotal pht\\r\\n\\t\\tLEFT OUTER JOIN [User] u ON (u.Oid = pht.[User])\\r\\n\\t\\tLEFT OUTER JOIN [UserTypology] ut ON (ut.Oid = u.Typology)\\r\\n\\t\\tLEFT OUTER JOIN [UserTypologyGroup] utg ON (utg.Oid = ut.UserTypologyGroup)\\r\\n\\t\\tLEFT OUTER JOIN [UserTypologyGroup] utgp ON (utgp.Oid = pht.UserTypologyGroup)\\r\\n\\t\\tLEFT OUTER JOIN [Department] utdp ON (utdp.Oid = ut.Department)\\r\\n\\t\\tLEFT OUTER JOIN \\r\\n\\t\\t(\\r\\n\\t\\t\\tSELECT \\r\\n\\t\\t\\t\\tutgdp.UserTypologyGroup,\\r\\n\\t\\t\\t\\tMax(utgdp.Department) as Department \\r\\n\\t\\t\\tFROM \\r\\n\\t\\t\\t\\t[UserTypologyGroupDepartment] utgdp \\r\\n\\t\\t\\tGROUP BY\\r\\n\\t\\t\\t\\tutgdp.UserTypologyGroup\\r\\n\\t\\t) utgpdp ON (utgpdp.UserTypologyGroup = utgp.Oid)\\r\\n\\t\\tLEFT OUTER JOIN Department utgdp ON (utgdp.Oid = utgpdp.Department)\\r\\n\\t\\tLEFT OUTER JOIN dbo.Estimate e ON (e.[Contract] = (select [Contract] from Project where Oid = @ProjectId))\\r\\n\\t\\tLEFT OUTER JOIN dbo.EstimateItem ei on (ei.Estimate = e.Oid)\\r\\n\\t\\tLEFT OUTER JOIN dbo.EstimateItemDetail eid on (eid.EstimateItem = ei.Oid AND eid.[Type] = 2 AND ((eid.Department = utdp.Oid OR eid.Department = utgdp.Oid) AND (eid.UserTypologyGroup = utgp.Oid OR eid.UserTypologyGroup = utg.Oid))),\\r\\n\\t\\tdbo.Project p\\r\\n\\tWHERE\\r\\n\\t\\tpht.GCRecord is null\\r\\n\\t\\tAND p.Oid = pht.Project\\r\\n\\t\\t/*[/ProjectFilter]*/ and pht.[Project] = @ProjectId /*[/ProjectFilter]*/\\r\\n\\tGROUP BY \\r\\n\\t\\tISNULL(utdp.[Name], utgdp.[Name]),\\r\\n\\t\\tISNULL(utgp.[Name], utg.[Name])\\r\\n) v\\r\\nGROUP BY\\r\\n\\tv.Department,\\r\\n\\tv.TypologyGroup\\r\\n\"}},\"Filters\":{},\"QueryConfiguration\":{}}]",
      "DashboardComponentType": {
        "Id": "7831bc23-b74a-48b2-95a7-130d290fd43b",
        "Name": "Generic Dashboard",
        "ComponentTypeNumber": 42
      },
      "AnalyticsApiUrl": "globalQuery/Analytics_Contracts_Per_Estimate_Service_Deliverable_TypologyGroup/execute",
      "Configuration": "{\n  \"height\": 300,\n  \"stateStoring\": {\n    \"enabled\": false\n  },\n  \"selection\": {\n    \"mode\": \"single\"\n  },\n  \"filterRow\": {\n    \"visible\": true\n  },\n  \"columnsAutoWidth\": true,\n  \"allowColumnResizing\": true,\n  \"columnResizingMode\": \"nextColumn\",\n  \"columnMinWidth\": 50,\n  \"scrolling\": {\n    \"mode\": \"virtual\"\n  },\n  \"columns\": [\n    {\n      \"dataField\": \"Department\",\n      \"caption\": \"Department\"\n    },\n    {\n      \"dataField\": \"TypologyGroup\",\n      \"caption\": \"Typology Group\"\n    },\n    {\n      \"dataField\": \"ContractedHours\",\n      \"caption\": \"Contracted\",\n      \"dataType\": \"number\",\n      \"format\": \"#,##0.00\",\n      \"allowGrouping\": false\n    },\n    {\n      \"dataField\": \"ContractedHoursIncome\",\n      \"caption\": \"Contracted Income\",\n      \"dataType\": \"number\",\n      \"format\": {\n        \"type\": \"currency\",\n        \"precision\": 2\n      },\n      \"displayFormat\": \"{0}\",\n      \"allowGrouping\": false\n    },\n    {\n      \"dataField\": \"ContractedActualIncomeVariation\",\n      \"caption\": \"Contracted - Actual\",\n      \"dataType\": \"number\",\n      \"format\": {\n        \"type\": \"currency\",\n        \"precision\": 2\n      },\n      \"displayFormat\": \"{0}\",\n      \"allowGrouping\": false\n    },\n    {\n      \"dataField\": \"ActualContractedPercentage\",\n      \"caption\": \"Actual / Contracted\",\n      \"dataType\": \"number\",\n      \"format\": \"percent\",\n      \"allowGrouping\": false,\n      \"cellTemplate\": \"function(e, i) { SW.setRAG(e, (i.value * 100.0).toFixed(1) + \u0027 %\u0027, i.value \u003e= 1.0, (i.value \u003e= 0.5 \u0026\u0026 i.value \u003c 1.0), i.value \u003c 0.5, true); }\"\n    },\n    {\n      \"dataField\": \"PlannedHours\",\n      \"caption\": \"Planned\",\n      \"dataType\": \"number\",\n      \"format\": \"#,##0.00\",\n      \"allowGrouping\": false\n    },\n    {\n      \"dataField\": \"PlannedHoursIncome\",\n      \"caption\": \"Planned Income\",\n      \"dataType\": \"number\",\n      \"format\": {\n        \"type\": \"currency\",\n        \"precision\": 2\n      },\n      \"displayFormat\": \"{0}\",\n      \"allowGrouping\": false\n    },\n    {\n      \"dataField\": \"ActualPlannedPercentage\",\n      \"caption\": \"Actual / Planned\",\n      \"dataType\": \"number\",\n      \"format\": \"percent\",\n      \"allowGrouping\": false,\n      \"cellTemplate\": \"function(e, i) { SW.setRAG(e, (i.value * 100.0).toFixed(1) + \u0027 %\u0027, i.value \u003e= 1.0, (i.value \u003e= 0.5 \u0026\u0026 i.value \u003c 1.0), i.value \u003c 0.5, true); }\"\n    },\n    {\n      \"dataField\": \"ActualHours\",\n      \"caption\": \"Actual\",\n      \"dataType\": \"number\",\n      \"format\": \"#,##0.00\",\n      \"allowGrouping\": false\n    },\n    {\n      \"dataField\": \"ActualHoursCost\",\n      \"caption\": \"Actual Cost\",\n      \"dataType\": \"number\",\n      \"format\": {\n        \"type\": \"currency\",\n        \"precision\": 2\n      },\n      \"displayFormat\": \"{0}\",\n      \"allowGrouping\": false\n    },\n    {\n      \"dataField\": \"ActualHoursIncome\",\n      \"caption\": \"Actual Income\",\n      \"dataType\": \"number\",\n      \"format\": {\n        \"type\": \"currency\",\n        \"precision\": 2\n      },\n      \"displayFormat\": \"{0}\",\n      \"allowGrouping\": false\n    }\n  ],\n  \"summary\": {\n    \"calculateCustomSummary\": \"function(options) {\n        if(options.name == \u0027ActualPlannedPercentageSummary\u0027) {\n            switch(options.summaryProcess) {\n                case \u0027start\u0027:\n                  options.totalValue = [0, 0];\n                  break;\n                case \u0027calculate\u0027:\n                  options.totalValue[0] = options.totalValue[0] + options.value.ActualHours;\n                  options.totalValue[1] = options.totalValue[1] + options.value.PlannedHours;\n                  break;\n                case \u0027finalize\u0027:\n                  if(Number(options.totalValue[1]) \u003e 0)\n                    options.totalValue = options.totalValue[0] / options.totalValue[1];\n                  else\n                    options.totalValue = 0;\n                  break;\n            }\n        }\n        if(options.name == \u0027ActualContractedPercentageSummary\u0027) {\n            switch(options.summaryProcess) {\n                case \u0027start\u0027:\n                  options.totalValue = [0,0];\n                  break;\n                case \u0027calculate\u0027:\n                  options.totalValue[0] = options.totalValue[0] + options.value.ActualHours;\n                  options.totalValue[1] = options.totalValue[1] + options.value.ContractedHours;\n                  break;\n                case \u0027finalize\u0027:\n                  if(Number(options.totalValue[1]) \u003e 0)\n                    options.totalValue = options.totalValue[0] / options.totalValue[1];\n                  else\n                    options.totalValue = 0;\n                  break;\n          }\n        }\n      }\",\n    \"totalItems\": [\n      {\n        \"name\": \"ActualPlannedPercentageSummary\",\n        \"showInColumn\": \"ActualPlannedPercentage\",\n        \"displayFormat\": \"{0}\",\n        \"valueFormat\": {\n          \"type\": \"percent\",\n          \"precision\": 1\n        },\n        \"summaryType\": \"custom\"\n      },\n      {\n        \"name\": \"ActualContractedPercentageSummary\",\n        \"showInColumn\": \"ActualContractedPercentage\",\n        \"displayFormat\": \"{0}\",\n        \"valueFormat\": {\n          \"type\": \"percent\",\n          \"precision\": 1\n        },\n        \"summaryType\": \"custom\"\n      },\n      {\n        \"column\": \"Department\",\n        \"summaryType\": \"count\"\n      },\n      {\n        \"column\": \"TypologyGroup\",\n        \"summaryType\": \"count\"\n      },\n      {\n        \"column\": \"ActualHours\",\n        \"summaryType\": \"sum\",\n        \"valueFormat\": \"#,##0.00\",\n        \"displayFormat\": \"{0}\"\n      },\n      {\n        \"column\": \"ActualHoursCost\",\n        \"summaryType\": \"sum\",\n        \"valueFormat\": {\n          \"type\": \"currency\",\n          \"precision\": 2\n        },\n        \"displayFormat\": \"{0}\"\n      },\n      {\n        \"column\": \"ActualHoursIncome\",\n        \"summaryType\": \"sum\",\n        \"valueFormat\": {\n          \"type\": \"currency\",\n          \"precision\": 2\n        },\n        \"displayFormat\": \"{0}\"\n      },\n      {\n        \"column\": \"PlannedHours\",\n        \"summaryType\": \"sum\",\n        \"valueFormat\": \"#,##0.00\",\n        \"displayFormat\": \"{0}\"\n      },\n      {\n        \"column\": \"PlannedHoursIncome\",\n        \"summaryType\": \"sum\",\n        \"valueFormat\": {\n          \"type\": \"currency\",\n          \"precision\": 2\n        },\n        \"displayFormat\": \"{0}\"\n      },\n      {\n        \"column\": \"ContractedHours\",\n        \"summaryType\": \"sum\",\n        \"valueFormat\": \"#,##0.00\",\n        \"displayFormat\": \"{0}\"\n      },\n      {\n        \"column\": \"ContractedHoursIncome\",\n        \"summaryType\": \"sum\",\n        \"valueFormat\": {\n          \"type\": \"currency\",\n          \"precision\": 2\n        },\n        \"displayFormat\": \"{0}\"\n      },\n      {\n        \"column\": \"ContractedActualIncomeVariation\",\n        \"summaryType\": \"sum\",\n        \"valueFormat\": {\n          \"type\": \"currency\",\n          \"precision\": 2\n        },\n        \"displayFormat\": \"{0}\"\n      }\n    ],\n    \"groupItems\": [\n      {\n        \"name\": \"ActualPlannedPercentageSummary\",\n        \"showInColumn\": \"ActualPlannedPercentage\",\n        \"displayFormat\": \"{0}\",\n        \"valueFormat\": {\n          \"type\": \"percent\",\n          \"precision\": 1\n        },\n        \"summaryType\": \"custom\",\n        \"showInGroupFooter\": true\n      },\n      {\n        \"name\": \"ActualContractedPercentageSummary\",\n        \"showInColumn\": \"ActualContractedPercentage\",\n        \"displayFormat\": \"{0}\",\n        \"valueFormat\": {\n          \"type\": \"percent\",\n          \"precision\": 1\n        },\n        \"summaryType\": \"custom\",\n        \"showInGroupFooter\": true\n      },\n      {\n        \"column\": \"Department\",\n        \"summaryType\": \"count\",\n        \"showInGroupFooter\": true\n      },\n      {\n        \"column\": \"TypologyGroup\",\n        \"summaryType\": \"count\",\n        \"showInGroupFooter\": true\n      },\n      {\n        \"column\": \"ActualHours\",\n        \"summaryType\": \"sum\",\n        \"valueFormat\": \"#,##0.00\",\n        \"displayFormat\": \"{0}\",\n        \"showInGroupFooter\": true\n      },\n      {\n        \"column\": \"ActualHoursCost\",\n        \"summaryType\": \"sum\",\n        \"valueFormat\": {\n          \"type\": \"currency\",\n          \"precision\": 2\n        },\n        \"displayFormat\": \"{0}\",\n        \"showInGroupFooter\": true\n      },\n      {\n        \"column\": \"ActualHoursIncome\",\n        \"summaryType\": \"sum\",\n        \"valueFormat\": {\n          \"type\": \"currency\",\n          \"precision\": 2\n        },\n        \"displayFormat\": \"{0}\",\n        \"showInGroupFooter\": true\n      },\n      {\n        \"column\": \"PlannedHours\",\n        \"summaryType\": \"sum\",\n        \"valueFormat\": \"#,##0.00\",\n        \"displayFormat\": \"{0}\",\n        \"showInGroupFooter\": true\n      },\n      {\n        \"column\": \"PlannedHoursIncome\",\n        \"summaryType\": \"sum\",\n        \"valueFormat\": {\n          \"type\": \"currency\",\n          \"precision\": 2\n        },\n        \"displayFormat\": \"{0}\",\n        \"showInGroupFooter\": true\n      },\n      {\n        \"column\": \"ContractedHours\",\n        \"summaryType\": \"sum\",\n        \"valueFormat\": \"#,##0.00\",\n        \"displayFormat\": \"{0}\",\n        \"showInGroupFooter\": true\n      },\n      {\n        \"column\": \"ContractedHoursIncome\",\n        \"summaryType\": \"sum\",\n        \"valueFormat\": {\n          \"type\": \"currency\",\n          \"precision\": 2\n        },\n        \"displayFormat\": \"{0}\",\n        \"showInGroupFooter\": true\n      },\n      {\n        \"column\": \"ContractedActualIncomeVariation\",\n        \"summaryType\": \"sum\",\n        \"valueFormat\": {\n          \"type\": \"currency\",\n          \"precision\": 2\n        },\n        \"displayFormat\": \"{0}\",\n        \"showInGroupFooter\": true\n      }\n    ]\n  }\n}",
      "DashboardDefinitionId": "496672c6-5fd0-4291-a32f-3690dfdd5e88"
    },
    {
      "Id": "965235cb-c68c-417e-bd48-fa2c35c023cd",
      "Name": "Monthly Distribution",
      "Active": true,
      "UseQuery": false,
      "Query": null,
      "Size": 8,
      "Order": 2,
      "Parameters": "[{\"WidgetSubTitle\":\"Planned Time, Utilization \u0026 Income\",\"WidgetType\":\"chart\",\"WidgetFilterField\":\"\",\"WidgetColor\":\"#efefef\",\"WidgetHeight\":\"300\",\"WidgetHeader\":{\"showContextInfo\":false,\"WidgetPeriodChooser\":{\"type\":\"year\",\"visible\":false},\"WidgetMetrics\":{\"visible\":true,\"Metrics\":[{\"visible\":true,\"metricName\":\"# Actual\",\"metricFieldValue\":\"ActualTimeGrandTotal\"},{\"visible\":true,\"metricName\":\"# Planned\",\"metricFieldValue\":\"PlannedTimeGrandTotal\"},{\"visible\":true,\"metricName\":\"# Contracted\",\"metricFieldValue\":\"ContractedTimeGrandTotal\"}]},\"showSubTitle\":true,\"showTitle\":true},\"WidgetDataSources\":{\"main\":{\"type\":\"querytext\",\"value\":\"with met as\\r\\n(\\r\\n    select  est.Oid as EstimateOid,\\r\\n            datefromparts(Year(yrd.Day), Month(yrd.Day), 1) as [Date],\\r\\n            count(*) over (partition by est.Oid) as Months\\r\\n    from    Contract cnt, Estimate est, YearDay yrd\\r\\n    where   est.Contract = cnt.Oid and\\r\\n            yrd.Day between cast(est.Date as date) and cast(est.Expiration as date) and\\r\\n            Day(yrd.Day) = Day(est.Date)\\r\\n            /*[ProjectFilter]*/ and cnt.Oid = (select [Contract] from Project where Oid = @ProjectId) /*[/ProjectFilter]*/\\r\\n),\\r\\nmpj as\\r\\n(\\r\\n    select  prj.Oid as ProjectOid,\\r\\n            datefromparts(Year(yrd.Day), Month(yrd.Day), 1) as [Date],\\r\\n            count(*) over (partition by prj.Oid) as Months\\r\\n    from    Contract cnt, Project prj, YearDay yrd\\r\\n    where   prj.Contract = cnt.Oid and\\r\\n            yrd.Day between cast(prj.BeginDate as date) and cast(prj.EndDate as date) and\\r\\n            Day(yrd.Day) = Day(prj.BeginDate)\\r\\n            /*[ProjectFilter]*/ and prj.Oid = @ProjectId /*[/ProjectFilter]*/\\r\\n)\\r\\nselect  [Date], \\r\\n        sum(ResourcesWithVatIncome) as ResourcesWithVatIncome,\\r\\n        sum(ResourcesWithVatCost) as ResourcesWithVatCost,\\r\\n        sum(ContractedTime) as ContractedTime,\\r\\n        sum(PlannedTime) as PlannedTime,\\r\\n        sum(ForecastTime) as ForecastTime,\\r\\n        sum(ActualTime) as ActualTime,\\r\\n        sum(sum(ContractedTime)) over() as ContractedTimeGrandTotal,\\r\\n        sum(sum(PlannedTime)) over() as PlannedTimeGrandTotal,\\r\\n        sum(sum(ForecastTime)) over() as ForecastTimeGrandTotal,\\r\\n        sum(sum(ActualTime)) over() as ActualTimeGrandTotal\\r\\nfrom    (\\r\\n            select  [Date],\\r\\n                    sum(ResourcesWithVatIncome) / max(Months) as ResourcesWithVatIncome,\\r\\n                    sum(ResourcesWithVatCost) / max(Months) as ResourcesWithVatCost,\\r\\n                    sum(ContractedTime) / max(Months) as ContractedTime,\\r\\n                    0 as PlannedTime,\\r\\n                    0 as ForecastTime,\\r\\n                    0 as ActualTime\\r\\n            from    (\\r\\n                    select  est.Oid as EstimateOid,\\r\\n                            sum(edt.ValueWithVatIncome * eit.Retainer) as ResourcesWithVatIncome,\\r\\n                            sum(edt.ValueWithVatCost * eit.Retainer) as ResourcesWithVatCost,\\r\\n                            sum(edt.Hours * eit.Retainer) as ContractedTime\\r\\n                    from    Estimate est, EstimateItem eit, EstimateItemDetail edt, Contract cnt\\r\\n                    where   est.Contract = cnt.Oid and\\r\\n                            eit.Estimate = est.Oid and\\r\\n                            edt.EstimateItem = eit.Oid and\\r\\n                            edt.Type = 2\\r\\n                            /*[ProjectFilter]*/ and cnt.Oid = (select [Contract] from Project where Oid = @ProjectId) /*[/ProjectFilter]*/\\r\\n                    group by est.Oid\\r\\n                    ) t, met\\r\\n            where   met.EstimateOid = t.EstimateOid\\r\\n            group by t.EstimateOid, [Date]  \\r\\n            union all\\r\\n            select  [Date],\\r\\n                    0 as ResourcesWithVatIncome,\\r\\n                    0 as ResourcesWithVatCost,\\r\\n                    0 as ContractedTime,\\r\\n                    sum(PlannedTime) / max(Months) as PlannedTime,\\r\\n                    0 as ForecastTime,\\r\\n                    0 as ActualTime\\r\\n            from    (\\r\\n                    select  prj.Oid as ProjectOid,\\r\\n                            sum(pht.PlannedMinutes / 60.0) as PlannedTime\\r\\n                    from    PlannedHoursTotal pht, Project prj, Contract cnt\\r\\n                    where   prj.Oid = pht.Project and\\r\\n                            prj.Contract = cnt.Oid and\\r\\n                            pht.GCRecord is null \\r\\n                            /*[ProjectFilter]*/ and prj.Oid = @ProjectId /*[/ProjectFilter]*/\\r\\n                    group by prj.Oid\\r\\n                    ) t, mpj\\r\\n            where   mpj.ProjectOid = t.ProjectOid\\r\\n            group by t.ProjectOid, [Date]  \\r\\n            union all\\r\\n            select  datefromparts(Year(pha.Date), Month(pha.Date), 1) as [Date],\\r\\n                    0 as ResourcesWithVatIncome,\\r\\n                    0 as ResourcesWithVatCost,\\r\\n                    0 as ContractedTime,\\r\\n                    0 as PlannedTime,\\r\\n                    sum(pha.AdjustmentMinutes / 60.0) as ForecastTime,\\r\\n                    0 as ActualTime\\r\\n            from    PlannedHoursAdjustment pha, Project prj, Contract cnt\\r\\n            where   prj.Oid = pha.Project and\\r\\n                    prj.Contract = cnt.Oid and\\r\\n                    pha.GCRecord is null \\r\\n                    /*[ProjectFilter]*/ and prj.Oid = @ProjectId /*[/ProjectFilter]*/\\r\\n            group by Year(pha.Date), Month(pha.Date)\\r\\n            union all\\r\\n            select  datefromparts(Year(tim.[Date]), Month(tim.[Date]), 1) as [Date],\\r\\n                    0 as ResourcesWithVatIncome,\\r\\n                    0 as ResourcesWithVatCost,\\r\\n                    0 as ContractedTime,\\r\\n                    0 as PlannedTime,\\r\\n                    0 as ForecastTime,\\r\\n                    sum(DurationHours + DurationMinutes / 60.0) as ActualTime\\r\\n            from    Timesheet tim, Project prj, Contract cnt\\r\\n            where   prj.Oid = tim.Project and\\r\\n                    prj.Contract = cnt.Oid\\r\\n                    /*[ProjectFilter]*/ and prj.Oid = @ProjectId /*[/ProjectFilter]*/\\r\\n            group by Year(tim.[Date]), Month(tim.[Date])\\r\\n        ) t\\r\\ngroup by [Date]\"}},\"Filters\":{},\"QueryConfiguration\":{}}]",
      "DashboardComponentType": {
        "Id": "7831bc23-b74a-48b2-95a7-130d290fd43b",
        "Name": "Generic Dashboard",
        "ComponentTypeNumber": 42
      },
      "AnalyticsApiUrl": "globalQuery/Analytics_Contracts_Per_Month/execute",
      "Configuration": "{\n  \"size\": {\n    \"height\": 270\n  },\n  \"commonSeriesSettings\": {\n    \"argumentField\": \"Date\"\n  },\n  \"commonPaneSettings\": {\n    \"border\": {\n      \"visible\": true\n    }\n  },\n  \"argumentAxis\": {\n    \"argumentType\": \"datetime\",\n    \"type\": \"discrete\",\n    \"label\": {\n      \"format\": \"month\",\n      \"font\": {\n        \"family\": \"Varela Round\"\n      }\n    }\n  },\n  \"legend\": {\n    \"rowCount\": 1,\n    \"verticalAlignment\": \"bottom\",\n    \"horizontalAlignment\": \"center\"\n  },\n  \"panes\": [\n    {\n      \"name\": \"Value\"\n    },\n    {\n      \"name\": \"Time\"\n    }\n  ],\n  \"valueAxis\": [\n    {\n      \"name\": \"Value\",\n      \"pane\": \"Value\",\n      \"title\": \"Value\",\n      \"label\": {\n        \"font\": {\n          \"family\": \"Varela Round\"\n        }\n      }\n    },\n    {\n      \"name\": \"Time\",\n      \"pane\": \"Time\",\n      \"title\": \"Time\",\n      \"label\": {\n        \"font\": {\n          \"family\": \"Varela Round\"\n        }\n      }\n    }\n  ],\n  \"series\": [\n    {\n      \"type\": \"bar\",\n      \"valueField\": \"ResourcesWithVatIncome\",\n      \"name\": \"Income\",\n      \"pane\": \"Value\"\n    },\n    {\n      \"type\": \"bar\",\n      \"valueField\": \"ResourcesWithVatCost\",\n      \"name\": \"Cost\",\n      \"pane\": \"Value\"\n    },\n    {\n      \"type\": \"bar\",\n      \"valueField\": \"ContractedTime\",\n      \"name\": \"Contracted Time\",\n      \"pane\": \"Time\"\n    },\n    {\n      \"type\": \"bar\",\n      \"valueField\": \"ForecastTime\",\n      \"name\": \"Forecast\",\n      \"pane\": \"Time\"\n    },\n    {\n      \"type\": \"bar\",\n      \"valueField\": \"ActualTime\",\n      \"name\": \"Actual Time\",\n      \"pane\": \"Time\"\n    }\n  ]\n}",
      "DashboardDefinitionId": "496672c6-5fd0-4291-a32f-3690dfdd5e88"
    }
  ],
  "Version": 2,
  "Default": true,
  "Dependencies": {
    "DashboardSdk": "1.0.0",
    "Analytics": "1.0.0",
    "SkillsWorkflow": "1.0.0"
  }
}